carg_io/__init__.py
carg_io/cargo.py
carg_io/core.py
carg_io/execeptions.py
carg_io/postprocessing.py
carg_io/spaces.py
carg_io-1.0b1.dist-info/AUTHORS.rst
carg_io-1.0b1.dist-info/LICENSE.txt
carg_io-1.0b1.dist-info/METADATA
carg_io-1.0b1.dist-info/WHEEL
carg_io-1.0b1.dist-info/top_level.txt
carg_io-1.0b1.dist-info/RECORD
