Metadata-Version: 2.1
Name: carg-io
Version: 1.0b1
Summary: Parametrization made easy
Author-email: "E. van Vliet" <eelcovanvliet@gmail.com>
Classifier: Development Status :: 4 - Beta
Classifier: Programming Language :: Python
Classifier: License :: OSI Approved :: MIT License
Classifier: Intended Audience :: Science/Research
Classifier: Topic :: Scientific/Engineering :: Visualization
Requires-Python: >=3.11
License-File: LICENSE.txt
License-File: AUTHORS.rst
Requires-Dist: numpy>=1.24.3
Requires-Dist: pandas>=2.0.0
Requires-Dist: Pint>=0.20.1
Requires-Dist: bokeh>=3.1.1
Requires-Dist: importlib-metadata; python_version < "3.8"
Provides-Extra: dev
Requires-Dist: sphinx; extra == "dev"
Requires-Dist: pytest; extra == "dev"
Requires-Dist: pytest-cov; extra == "dev"
Requires-Dist: furo; extra == "dev"
Requires-Dist: build; extra == "dev"
Requires-Dist: twine; extra == "dev"
